pylars_misc/__init__.py
pylars_misc/pylars_misc.py
pylars_misc-2023.5.1.dist-info/METADATA
pylars_misc-2023.5.1.dist-info/WHEEL
pylars_misc-2023.5.1.dist-info/top_level.txt
pylars_misc-2023.5.1.dist-info/RECORD
