Metadata-Version: 2.1
Name: pylars-misc
Version: 2023.5.1
Summary: python polars with convenience functions bolted on
Author-email: Dean MacGregor <dm121@yahoo.com>
Requires-Python: >=3.7
